mult/adder.v
module adder(
  input a, 
  input b, 
  input cin, 
  output reg carry, 
  output reg sum 
);
reg [1:0] s1;
always@(a,b,cin) begin 
  s1 = {1'b0,a} + {1'b0,b} + {1'b0,cin};
end
assign carry = s1[1];
assign sum   = s1[0];
endmodule

mult/mult.v
module mult (
  input clock,
  input [3:0] a,
  input [3:0] b,
  output reg [7:0] S
);
reg [3:0] s0, s1, s2, s3, s0_help_1, s0_help_2, s0_help_3, s1_help_1, s1_help_2, s1_help_3, s1_help_4;
reg [3:0] s2_help_1, s2_help_2, s2_help_3, s3_help_1, s3_help_2, s3_help_3, s3_help_4;
reg [7:0] c_temp;
reg [5:0] sum1_temp, carry1_temp, sum2_temp, carry2_temp;
reg [2:0] c1_var, c2_var;
reg [4:0] c_var;
reg [5:0] s1_var, s2_var, s1_var_1, s1_var_2, s2_var_1, s2_var_2, s2_var_3, s2_var_4, s2_var_5, s1_var_3;
reg [6:0] teliko_1, teliko_2, teliko_3, teliko_4, teliko_5, teliko_6;

always@(b)begin 
  if(b[3] == 0) begin 
    s3 <= 0;
  end else begin
    s3 <= a;
  end
  if(b[2] == 0) begin 
    s2 <= 0;
  end else begin
    s2 <= a;
  end
  if(b[1] == 0) begin 
    s1 <= 0;
  end else begin
    s1 <= a;
  end
  if(b[0] == 0) begin 
    s0 <= 0;
  end else begin
    s0 <= a;
  end
end 


always@(posedge clock)begin 

  c1_var[0] <= carry1_temp[0];
  c1_var[1] <= carry1_temp[1];
  c1_var[2] <= carry1_temp[2];
  c2_var[0] <= carry2_temp[0];
  c2_var[1] <= carry2_temp[1];
  c2_var[2] <= carry2_temp[2];
  c_var[0] <= c_temp[0];
  c_var[1] <= c_temp[1];
  c_var[2] <= c_temp[2];
  c_var[3] <= c_temp[3];
  c_var[4] <= c_temp[4];
  s1_var[0] <= sum1_temp[0];
  s1_var[1] <= sum1_temp[1];
  s1_var_1[0] <= s1_var[0];
  s1_var_2[0] <= s1_var_1[0];
  s1_var_1[1] <= s1_var[1];
  s1_var_2[1] <= s1_var_1[1];

  s1_var[2] <= sum1_temp[2];
  s1_var_1[2] <= s1_var[2];
  s1_var_2[2] <= s1_var_1[2];
  s1_var[3] <= sum1_temp[3];
  s1_var_1[3] <= s1_var[3];
  s1_var_2[3] <= s1_var_1[3];
  s1_var[4] <= sum1_temp[4];
  s1_var_1[4] <= s1_var[4];
  s1_var_2[4] <= s1_var_1[4];
  s1_var[5] <= sum1_temp[5];
  s1_var_1[5] <= s1_var[5];
  s1_var_2[5] <= s1_var_1[5];
  s1_var_3[5] <= s1_var_2[5];
  s2_var[0] <= sum2_temp[0];
  s2_var[1] <= sum2_temp[1];
  s2_var_1[0] <= s2_var[0];
  s2_var_2[0] <= s2_var_1[0];
  s2_var_3[0] <= s2_var_2[0];
  s2_var_1[1] <= s2_var[1];
  s2_var_2[1] <= s2_var_1[1];
  s2_var_3[1] <= s2_var_2[1];
  s2_var_4[1]<= s2_var_3[1];


  s2_var[2] <= sum2_temp[2];
  s2_var_1[2] <= s2_var[2];
  s2_var_2[2] <= s2_var_1[2];
  s2_var_3[2] <= s2_var_2[2];
  s2_var_4[2] <= s2_var_3[2];
  s2_var[3] <= sum2_temp[3];
  s2_var_1[3] <= s2_var[3];
  s2_var_2[3] <= s2_var_1[3];
  s2_var_3[3] <= s2_var_2[3];
  s2_var_4[3] <= s2_var_3[3];

  s2_var[4] <= sum2_temp[4];
  s2_var_1[4] <= s2_var[4];
  s2_var_2[4] <= s2_var_1[4];
  s2_var_3[4] <= s2_var_2[4];
  s2_var_4[4] <= s2_var_3[4];
  s2_var[5] <= sum2_temp[5];
  s2_var_1[5] <= s2_var[5];
  s2_var_2[5] <= s2_var_1[5];
  s2_var_3[5] <= s2_var_2[5];
  s2_var_4[5] <= s2_var_3[5];
  s2_var_5[5] <= s2_var_4[5];

  s0_help_1 <= s0;
  s0_help_2 <= s0_help_1; 
  s0_help_3 <= s0_help_2;
  s1_help_1 <= s1;
  s1_help_2 <= s1_help_1; 
  s1_help_3 <= s1_help_2;
  s1_help_4 <= s1_help_3;
  s2_help_1 <= s2;
  s2_help_2 <= s2_help_1; 
  s2_help_3 <= s2_help_2;
  s3_help_1 <= s3;
  s3_help_2 <= s3_help_1; 
  s3_help_3 <= s3_help_2;
  s3_help_4 <= s3_help_3;

  S[6] <= teliko_1[6];

  teliko_1[5]<= teliko_2[5];
  S[5] <= teliko_1[5];

  teliko_2[4]<= teliko_3[4];
  teliko_1[4]<= teliko_2[4];
  S[4] <= teliko_1[4];

  teliko_3[3]<= teliko_4[3];
  teliko_2[3]<= teliko_3[3];
  teliko_1[3]<= teliko_2[3];
  S[3] <= teliko_1[3];

  teliko_4[2]<= teliko_5[2];
  teliko_3[2]<= teliko_4[2];
  teliko_2[2]<= teliko_3[2];
  teliko_1[2]<= teliko_2[2];
  S[2] <= teliko_1[2];

  teliko_6[0]<= s1_var_2[0];
  teliko_5[0] <= teliko_6[0];
  teliko_4[0]<= teliko_5[0];
  teliko_3[0]<= teliko_4[0];
  teliko_2[0]<= teliko_3[0];
  S[0]<= teliko_2[0];


  teliko_5[1]<= s1_var_2[1];

  teliko_4[1]<= teliko_5[1];
  teliko_3[1]<= teliko_4[1];
  teliko_2[1]<= teliko_3[1];
  teliko_1[1]<= teliko_2[1];
  S[1] <= teliko_1[1];
end 

assign sum1_temp[0] = s0[0];
assign sum2_temp[0] = s2[0];

adder fa1(.a(s0[1]),.b(s1[0]),.cin(1'b0),.sum(sum1_temp[1]),.carry(carry1_temp[0]));
adder fa2(.a(s0_help_1[2]),.b(s1_help_1[1]),.cin(c1_var[0]),.sum(sum1_temp[2]),.carry(carry1_temp[1]));
adder fa3(.a(s0_help_2[3]),.b(s1_help_2[2]),.cin(c1_var[1]),.sum(sum1_temp[3]),.carry(carry1_temp[2]));
adder fa4(.a(1'b0),.b(s1_help_3[3]),.cin(c1_var[2]),.sum(sum1_temp[4]),.carry(sum1_temp[5]));


adder fa5(.a(s2[1]),.b(s3[0]),.cin(1'b0),.sum(sum2_temp[1]),.carry(carry2_temp[0]));
adder fa6(.a(s2_help_1[2]),.b(s3_help_1[1]),.cin(c2_var[0]),.sum(sum2_temp[2]),.carry(carry2_temp[1]));
adder fa7(.a(s2_help_2[3]),.b(s3_help_2[2]),.cin(c2_var[1]),.sum(sum2_temp[3]),.carry(carry2_temp[2]));

adder fa8(.a(1'b0),.b(s3_help_3[3]),.cin(c2_var[2]),.sum(sum2_temp[4]),.carry(sum2_temp[5]));

adder fa9(.a(s1_var_2[2]),.b(s2_var_3[0]),.cin(1'b0),.sum(teliko_5[2]),.carry(c_temp[0])); 
adder fa10(.a( s1_var_2[3]),.b(s2_var_4[1]),.cin(c_var[0]),.sum(teliko_4[3]),.carry(c_temp[1])); 

adder fa11(.a(s1_var_2[4]),.b(s2_var_4[2]),.cin(c_var[1]),.sum(teliko_3[4]),.carry(c_temp[2])); 

adder fa12(.a(s1_var_3[5]),.b(s2_var_4[3]),.cin(c_var[2]),.sum(teliko_2[5]),.carry(c_temp[3])); 
adder fa13(.a(1'b0),.b(s2_var_4[4]),.cin(c_var[3]),.sum(teliko_1[6]),.carry(c_temp[4])); 
adder fa14(.a(1'b0),.b(s2_var_5[5]),.cin(c_var[4]),.sum(S[7]),.carry(c_temp[5])); 
endmodule

mult/mult_tb.sv
`timescale 1ns/1ns
module mult_tb; 
  logic clock;
  logic [3:0] a, b;
  wire [7:0] sum;

    
  mult dut(.clock(clock),.a(a),.b(b),.S(sum));
  initial begin 
    $dumpfile("mult.vcd");
    $dumpvars(0, mult_tb);
    a   <= 0;
    b   <= 0;
    clock <=0;
    #10
    for (int i= 0;i<=15;i++) begin 
      for (int j=0;j<=15;j++) begin 
        a   <= i;
        b   <= j;
        #5 clock = ~clock;
        #5 clock = ~clock;
        $display("Time=%5dt, a=0d%02d,b=0d%02d,mult=0d%03d",$time,a,b,sum);
      end 
    end
    for(int i=0;i<8;i++) begin 
        #5 clock = ~clock;
        #5 clock = ~clock;
        $display("Time=%5dt, a=0d%02d,b=0d%02d,mult=0d%03d",$time,a,b,sum);
    end
  end
endmodule

mult/mult.vcd
$date
	Thu Aug 17 21:57:31 2023
$end
$version
	Icarus Verilog
$end
$timescale
	1ns
$end
$scope module mult_tb $end
$var wire 8 ! sum [7:0] $end
$var reg 4 " a [3:0] $end
$var reg 4 # b [3:0] $end
$var reg 1 $ clock $end
$scope module dut $end
$var wire 4 % a [3:0] $end
$var wire 4 & b [3:0] $end
$var wire 1 $ clock $end
$var wire 7 ' teliko_5 [6:0] $end
$var wire 7 ( teliko_4 [6:0] $end
$var wire 7 ) teliko_3 [6:0] $end
$var wire 7 * teliko_2 [6:0] $end
$var wire 7 + teliko_1 [6:0] $end
$var wire 6 , sum2_temp [5:0] $end
$var wire 6 - sum1_temp [5:0] $end
$var wire 6 . carry2_temp [5:0] $end
$var wire 6 / carry1_temp [5:0] $end
$var wire 8 0 c_temp [7:0] $end
$var wire 8 1 S [7:0] $end
$var reg 3 2 c1_var [2:0] $end
$var reg 3 3 c2_var [2:0] $end
$var reg 5 4 c_var [4:0] $end
$var reg 4 5 s0 [3:0] $end
$var reg 4 6 s0_help_1 [3:0] $end
$var reg 4 7 s0_help_2 [3:0] $end
$var reg 4 8 s0_help_3 [3:0] $end
$var reg 4 9 s1 [3:0] $end
$var reg 4 : s1_help_1 [3:0] $end
$var reg 4 ; s1_help_2 [3:0] $end
$var reg 4 < s1_help_3 [3:0] $end
$var reg 4 = s1_help_4 [3:0] $end
$var reg 6 > s1_var [5:0] $end
$var reg 6 ? s1_var_1 [5:0] $end
$var reg 6 @ s1_var_2 [5:0] $end
$var reg 6 A s1_var_3 [5:0] $end
$var reg 4 B s2 [3:0] $end
$var reg 4 C s2_help_1 [3:0] $end
$var reg 4 D s2_help_2 [3:0] $end
$var reg 4 E s2_help_3 [3:0] $end
$var reg 6 F s2_var [5:0] $end
$var reg 6 G s2_var_1 [5:0] $end
$var reg 6 H s2_var_2 [5:0] $end
$var reg 6 I s2_var_3 [5:0] $end
$var reg 6 J s2_var_4 [5:0] $end
$var reg 6 K s2_var_5 [5:0] $end
$var reg 4 L s3 [3:0] $end
$var reg 4 M s3_help_1 [3:0] $end
$var reg 4 N s3_help_2 [3:0] $end
$var reg 4 O s3_help_3 [3:0] $end
$var reg 4 P s3_help_4 [3:0] $end
$var reg 7 Q teliko_6 [6:0] $end
$scope module fa1 $end
$var wire 1 R a $end
$var wire 1 S b $end
$var wire 1 T cin $end
$var wire 1 U sum $end
$var wire 1 V carry $end
$var reg 2 W s1 [1:0] $end
$upscope $end
$scope module fa10 $end
$var wire 1 X a $end
$var wire 1 Y b $end
$var wire 1 Z cin $end
$var wire 1 [ sum $end
$var wire 1 \ carry $end
$var reg 2 ] s1 [1:0] $end
$upscope $end
$scope module fa11 $end
$var wire 1 ^ a $end
$var wire 1 _ b $end
$var wire 1 ` cin $end
$var wire 1 a sum $end
$var wire 1 b carry $end
$var reg 2 c s1 [1:0] $end
$upscope $end
$scope module fa12 $end
$var wire 1 d a $end
$var wire 1 e b $end
$var wire 1 f cin $end
$var wire 1 g sum $end
$var wire 1 h carry $end
$var reg 2 i s1 [1:0] $end
$upscope $end
$scope module fa13 $end
$var wire 1 j a $end
$var wire 1 k b $end
$var wire 1 l cin $end
$var wire 1 m sum $end
$var wire 1 n carry $end
$var reg 2 o s1 [1:0] $end
$upscope $end
$scope module fa14 $end
$var wire 1 p a $end
$var wire 1 q b $end
$var wire 1 r cin $end
$var wire 1 s sum $end
$var wire 1 t carry $end
$var reg 2 u s1 [1:0] $end
$upscope $end
$scope module fa2 $end
$var wire 1 v a $end
$var wire 1 w b $end
$var wire 1 x cin $end
$var wire 1 y sum $end
$var wire 1 z carry $end
$var reg 2 { s1 [1:0] $end
$upscope $end
$scope module fa3 $end
$var wire 1 | a $end
$var wire 1 } b $end
$var wire 1 ~ cin $end
$var wire 1 !" sum $end
$var wire 1 "" carry $end
$var reg 2 #" s1 [1:0] $end
$upscope $end
$scope module fa4 $end
$var wire 1 $" a $end
$var wire 1 %" b $end
$var wire 1 &" cin $end
$var wire 1 '" sum $end
$var wire 1 (" carry $end
$var reg 2 )" s1 [1:0] $end
$upscope $end
$scope module fa5 $end
$var wire 1 *" a $end
$var wire 1 +" b $end
$var wire 1 ," cin $end
$var wire 1 -" sum $end
$var wire 1 ." carry $end
$var reg 2 /" s1 [1:0] $end
$upscope $end
$scope module fa6 $end
$var wire 1 0" a $end
$var wire 1 1" b $end
$var wire 1 2" cin $end
$var wire 1 3" sum $end
$var wire 1 4" carry $end
$var reg 2 5" s1 [1:0] $end
$upscope $end
$scope module fa7 $end
$var wire 1 6" a $end
$var wire 1 7" b $end
$var wire 1 8" cin $end
$var wire 1 9" sum $end
$var wire 1 :" carry $end
$var reg 2 ;" s1 [1:0] $end
$upscope $end
$scope module fa8 $end
$var wire 1 <" a $end
$var wire 1 =" b $end
$var wire 1 >" cin $end
$var wire 1 ?" sum $end
$var wire 1 @" carry $end
$var reg 2 A" s1 [1:0] $end
$upscope $end
$scope module fa9 $end
$var wire 1 B" a $end
$var wire 1 C" b $end
$var wire 1 D" cin $end
$var wire 1 E" sum $end
$var wire 1 F" carry $end
$var reg 2 G" s1 [1:0] $end
$upscope $end
$upscope $end
$scope begin $ivl_for_loop0 $end
$var integer 32 H" i [31:0] $end
$scope begin $ivl_for_loop1 $end
$var integer 32 I" j [31:0] $end
$upscope $end
$upscope $end
$scope begin $ivl_for_loop2 $end
$var integer 32 J" i [31:0] $end
$upscope $end
$upscope $end
$enddefinitions $end
$comment Show the parameter values. $end
$dumpall
$end
#0
$dumpvars
b0 J"
b0 I"
b0 H"
bx G"
xF"
xE"
0D"
xC"
xB"
bx A"
x@"
x?"
x>"
x="
0<"
bx ;"
x:"
x9"
x8"
x7"
x6"
bx 5"
x4"
x3"
x2"
x1"
x0"
b0 /"
0."
0-"
0,"
0+"
0*"
bx )"
x("
x'"
x&"
x%"
0$"
bx #"
x""
x!"
x~
x}
x|
bx {
xz
xy
xx
xw
xv
bx u
xt
xs
xr
xq
0p
bx o
xn
xm
xl
xk
0j
bx i
xh
xg
xf
xe
xd
bx c
xb
xa
x`
x_
x^
bx ]
x\
x[
xZ
xY
xX
b0 W
0V
0U
0T
0S
0R
bx Q
bx P
bx O
bx N
bx M
b0 L
bx K
bx J
bx I
bx H
bx G
bx F
bx E
bx D
bx C
b0 B
bx A
bx @
bx ?
bx >
bx =
bx <
bx ;
bx :
b0 9
bx 8
bx 7
bx 6
b0 5
bx 4
bx 3
bx 2
bxzzzzzzz 1
bzxxxxxx 0
bzxx0 /
bzxx0 .
bx00 -
bx00 ,
bxzzzzzz +
bzxzzzzz *
bzxzzzz )
bzxzzz (
bzxzz '
b0 &
b0 %
0$
b0 #
b0 "
bxzzzzzzz !
$end
#15
bzx00 .
04"
bx000 ,
03"
bzx00 /
0z
bx000 -
0y
b0 5"
b0 {
01"
00"
0w
0v
02"
0x
bzxxx '
bzxxzz (
bzxxzzz )
bzxxzzzz *
bxzzzzz +
bxzzzzzz !
bxzzzzzz 1
b0 M
b0 C
b0 :
b0 6
bx00 F
bx00 >
bx0 3
bx0 2
1$
#20
b1 #
b1 &
b1 I"
0$
#25
bz000 .
0:"
bx0000 ,
09"
bz000 /
0""
bx0000 -
0!"
b0 ;"
b0 #"
07"
06"
0}
0|
08"
0~
bzxxx '
bzxxxx (
bzxxxzz )
bzxxxzzz *
bxzzzz +
bxzzzzz !
bxzzzzz 1
b0 N
b0 D
b0 ;
b0 7
bx000 F
bx00 G
bx000 >
bx00 ?
bx00 3
bx00 2
1$
#30
b10 #
b10 &
b10 I"
0$
#35
0@"
b0 ,
0?"
0("
b0 -
0'"
b0 A"
b0 )"
0="
0%"
0>"
0&"
bzxxx '
bzxxxx (
bzxxxxx )
bzxxxxzz *
bxzzz +
bxzzzz !
bxzzzz 1
b0 O
b0 E
b0 <
b0 8
bx0000 F
bx000 G
bx00 H
bx0000 >
bx000 ?
bx00 @
b0 3
b0 2
1$
#40
b11 #
b11 &
b11 I"
0$
#45
bzxxxxx0 0
0F"
0E"
b0 G"
0C"
0B"
bz00x '
bx0 Q
bzxxxx (
bzxxxxx )
bzxxxxxx *
bxzz +
bxzzz !
bxzzz 1
b0 P
b0 =
b0 F
bx0000 G
bx000 H
bx00 I
b0 >
bx0000 ?
bx000 @
1$
#50
b100 #
b100 &
b100 I"
0$
#55
bzxxxx00 0
0\
0[
b0 ]
0Y
0X
0Z
bz000 '
bz000x (
bzxxxxx )
bzxxxxxx *
bxz +
bxzx !
bxzx 1
b0 G
bx0000 H
bx000 I
bx0x J
b0 ?
bx0000 @
bx0 4
1$
#60
b101 #
b101 &
b101 I"
0$
#65
bzxxx000 0
0b
0a
b0 c
0_
0^
0`
bz000 '
bz0000 (
bz0000x )
bzxxxxxx *
bxz +
bx !
bx 1
b0 H
bx0000 I
bx00x J
b0 @
bx00 4
1$
#70
b110 #
b110 &
b110 I"
0$
#75
bzxx0000 0
0h
0g
b0 i
0e
0d
0f
bz000 '
bz0000 (
bz00000 )
bz00000x *
bxz +
bx !
bx 1
b0 I
bx000x J
b0xxxxx A
bx000 4
1$
#80
b111 #
b111 &
b111 I"
0$
#85
bzx00000 0
0n
0m
b0 o
0k
0l
bz000 '
bz0000 (
bz00000 )
bz000000 *
b0z +
bx !
bx 1
b0x J
bx0000 4
1$
#90
b1000 #
b1000 &
b1000 I"
0$
#95
bz000000 0
0t
0s
b0 u
0q
0r
bz000 '
bz0000 (
bz00000 )
bz000000 *
b0z +
b0 !
b0 1
b0xxxxx K
b0 4
1$
#100
b1001 #
b1001 &
b1001 I"
0$
#105
bz000 '
bz0000 (
bz00000 )
bz000000 *
b0z +
b0 !
b0 1
1$
#110
b1010 #
b1010 &
b1010 I"
0$
#115
bz000 '
bz0000 (
bz00000 )
bz000000 *
b0z +
b0 !
b0 1
1$
#120
b1011 #
b1011 &
b1011 I"
0$
#125
bz000 '
bz0000 (
bz00000 )
bz000000 *
b0z +
b0 !
b0 1
1$
#130
b1100 #
b1100 &
b1100 I"
0$
#135
bz000 '
bz0000 (
bz00000 )
bz000000 *
b0z +
b0 !
b0 1
1$
#140
b1101 #
b1101 &
b1101 I"
0$
#145
bz000 '
bz0000 (
bz00000 )
bz000000 *
b0z +
b0 !
b0 1
1$
#150
b1110 #
b1110 &
b1110 I"
0$
#155
bz000 '
bz0000 (
bz00000 )
bz000000 *
b0z +
b0 !
b0 1
1$
#160
b1111 #
b1111 &
b1111 I"
0$
#165
bz000 '
bz0000 (
bz00000 )
bz000000 *
b0z +
b0 !
b0 1
1$
#170
b0 #
b0 &
b1 "
b1 %
b1 H"
b0 I"
0$
#175
bz000 '
bz0000 (
bz00000 )
bz000000 *
b0z +
b0 !
b0 1
1$
#180
b1 -
b1 5
b1 #
b1 &
b1 I"
0$
#185
bz000 '
bz0000 (
bz00000 )
bz000000 *
b0z +
b0 !
b0 1
b1 6
b1 >
1$
#190
1U
b1 W
b10 -
1S
b0 5
b1 9
b10 #
b10 &
b10 I"
0$
#195
bz000 '
bz0000 (
bz00000 )
bz000000 *
b0z +
b0 !
b0 1
b1 :
b1 7
b0 6
b1 ?
b10 >
1$
#200
b11 -
b1 5
b11 #
b11 &
b11 I"
0$
#205
bz000 '
bz0000 (
bz00000 )
bz000000 *
b0z +
b0 !
b0 1
b1 ;
b1 8
b0 7
b1 6
b1 @
b10 ?
b11 >
1$
#210
0U
b0 W
b0 -
0S
b1 ,
b0 5
b0 9
b1 B
b100 #
b100 &
b100 I"
0$
#215
bz000 '
bx1 Q
bz0000 (
bz00000 )
bz000000 *
b0z +
b0 !
b0 1
b1 C
b1 <
b0 :
b0 8
b1 7
b0 6
b1 F
b10 @
b11 ?
b0 >
1$
#220
b1 -
b1 5
b101 #
b101 &
b101 I"
0$
#225
bz011 '
bx0 Q
bz0000 (
bz00000 )
bz000000 *
b0z +
b0 !
b0 1
b1 D
b1 =
b0 ;
b1 8
b0 7
b1 6
b1 G
b11 @
b0 ?
b1 >
1$
#230
1U
b1 W
b10 -
1S
b0 5
b1 9
b110 #
b110 &
b110 I"
0$
#235
bz010 '
bx1 Q
bz0011 (
bz00000 )
bz000000 *
b0z +
b0 !
b0 1
b1 E
b0 <
b1 :
b0 8
b1 7
b0 6
b1 H
b0 @
b1 ?
b10 >
1$
#240
b11 -
b1 5
b111 #
b111 &
b111 I"
0$
#245
1E"
b1 G"
1C"
bz101 '
bx0 Q
bz0010 (
bz00011 )
bz000000 *
b0z +
b0 !
b0 1
b0 =
b1 ;
b1 8
b0 7
b1 6
b1 I
b1 @
b10 ?
b11 >
1$
#250
0U
1-"
b0 W
b1 /"
b0 -
0S
b10 ,
1+"
b0 5
b0 9
b0 B
b1 L
b1000 #
b1000 &
b1000 I"
0$
#255
bz100 '
bx1 Q
bz0101 (
bz00010 )
bz000011 *
b0z +
b0 !
b0 1
b1 M
b0 C
b1 <
b0 :
b0 8
b1 7
b0 6
b10 F
b10 @
b11 ?
b0 >
1$
#260
b1 -
b1 5
b1001 #
b1001 &
b1001 I"
0$
#265
bz111 '
bx0 Q
bz0100 (
bz00101 )
bz000010 *
b1z +
b1 !
b1 1
b1 N
b0 D
b1 =
b0 ;
b1 8
b0 7
b1 6
b10 G
b11 @
b0 ?
b1 >
1$
#270
1U
b1 W
b10 -
1S
b0 5
b1 9
b1010 #
b1010 &
b1010 I"
0$
#275
bz110 '
bx1 Q
bz0111 (
bz00100 )
bz000101 *
b1z +
b10 !
b10 1
b1 O
b0 E
b0 <
b1 :
b0 8
b1 7
b0 6
b10 H
b0 @
b1 ?
b10 >
1$
#280
b11 -
b1 5
b1011 #
b1011 &
b1011 I"
0$
#285
0E"
b0 G"
0C"
bz001 '
bx0 Q
bz0110 (
bz00111 )
bz000100 *
b10z +
b11 !
b11 1
b1 P
b0 =
b1 ;
b1 8
b0 7
b1 6
b10 I
b1 @
b10 ?
b11 >
1$
#290
0U
b0 W
b0 -
0S
b11 ,
b0 5
b0 9
b1 B
b1100 #
b1100 &
b1100 I"
0$
#295
1[
b1 ]
1Y
bz000 '
bx1 Q
bz1001 (
bz00110 )
bz000111 *
b10z +
b100 !
b100 1
b1 C
b1 <
b0 :
b0 8
b1 7
b0 6
b1x J
b11 F
b10 @
b11 ?
b0 >
1$
#300
b1 -
b1 5
b1101 #
b1101 &
b1101 I"
0$
#305
bz011 '
bx0 Q
bz1000 (
bz01001 )
bz000110 *
b11z +
b101 !
b101 1
b1 D
b1 =
b0 ;
b1 8
b0 7
b1 6
b11 G
b11 @
b0 ?
b1 >
1$
#310
1U
b1 W
b10 -
1S
b0 5
b1 9
b1110 #
b1110 &
b1110 I"
0$
#315
bz010 '
bx1 Q
bz1011 (
bz01000 )
bz001001 *
b11z +
b110 !
b110 1
b1 E
b0 <
b1 :
b0 8
b1 7
b0 6
b11 H
b0 @
b1 ?
b10 >
1$
#320
b11 -
b1 5
b1111 #
b1111 &
b1111 I"
0$
#325
1E"
b1 G"
1C"
bz101 '
bx0 Q
bz1010 (
bz01011 )
bz001000 *
b100z +
b111 !
b111 1
b0 =
b1 ;
b1 8
b0 7
b1 6
b11 I
b1 @
b10 ?
b11 >
1$
#330
0U
0-"
b0 W
b0 /"
b0 -
0S
b0 ,
0+"
b0 5
b0 9
b0 B
b0 L
b0 #
b0 &
b10 "
b10 %
b10 H"
b0 I"
0$
#335
bz100 '
bx1 Q
bz1101 (
bz01010 )
bz001011 *
b100z +
b1000 !
b1000 1
b0 M
b0 C
b1 <
b0 :
b0 8
b1 7
b0 6
b0 F
b10 @
b11 ?
b0 >
1$
#340
b10 -
1U
b1 W
1R
b10 5
b1 #
b1 &
b1 I"
0$
#345
bz111 '
bx0 Q
bz1100 (
bz01101 )
bz001010 *
b101z +
b1001 !
b1001 1
b0 N
b0 D
b1 =
b0 ;
b1 8
b0 7
b10 6
b0 G
b11 @
b0 ?
b10 >
1$
#350
b0 -
0U
b0 W
0R
b0 5
b10 9
b10 #
b10 &
b10 I"
0$
#355
b100 -
1y
b1 {
1w
bz110 '
bx1 Q
bz1111 (
bz01100 )
bz001101 *
b101z +
b1010 !
b1010 1
b0 O
b0 E
b0 <
b10 :
b0 8
b10 7
b0 6
b0 H
b10 ?
b0 @
b0 >
1$
#360
b110 -
1U
b1 W
1R
b10 5
b11 #
b11 &
b11 I"
0$
#365
0E"
b0 G"
0C"
bz001 '
bx0 Q
bz1110 (
bz01111 )
bz001100 *
b110z +
b1011 !
b1011 1
b0 P
b0 =
b10 ;
b10 8
b0 7
b10 6
b0 I
b10 @
b0 ?
b110 >
1$
#370
b100 -
0U
b10 ,
1-"
b0 W
b1 /"
0R
1*"
b0 5
b0 9
b10 B
b100 #
b100 &
b100 I"
0$
#375
b0 -
0y
0[
b0 {
b0 ]
0w
0Y
bz010 '
bz0001 (
bz01110 )
bz001111 *
b110z +
b1100 !
b1100 1
b10 C
b10 <
b0 :
b0 8
b10 7
b0 6
b0x J
b10 F
b0 @
b110 ?
b100 >
1$
#380
b10 -
1U
b1 W
1R
b10 5
b101 #
b101 &
b101 I"
0$
#385
1E"
b1 G"
1B"
bz100 '
bz0010 (
bz00001 )
bz001110 *
b111z +
b1101 !
b1101 1
b10 D
b10 =
b0 ;
b10 8
b0 7
b10 6
b10 G
b110 @
b100 ?
b10 >
1$
#390
b0 -
0U
b0 W
0R
b0 5
b10 9
b110 #
b110 &
b110 I"
0$
#395
b100 -
1y
b1 {
1w
bz110 '
bz0100 (
bz00010 )
bz000001 *
b111z +
b1110 !
b1110 1
b10 E
b0 <
b10 :
b0 8
b10 7
b0 6
b10 H
b100 @
b10 ?
b0 >
1$
#400
b110 -
1U
b1 W
1R
b10 5
b111 #
b111 &
b111 I"
0$
#405
0E"
b0 G"
0B"
bz000 '
bz0110 (
bz00100 )
bz000010 *
b0z +
b1111 !
b1111 1
b0 =
b10 ;
b10 8
b0 7
b10 6
b10 I
b10 @
b0 ?
b110 >
1$
#410
b100 -
0U
b0 ,
0-"
b0 W
b0 /"
0R
0*"
b0 5
b0 9
b0 B
b10 L
b1000 #
b1000 &
b1000 I"
0$
#415
b100 ,
13"
b0 -
0y
1[
b1 5"
b0 {
b1 ]
11"
0w
1Y
bz010 '
bz1000 (
bz00110 )
bz000100 *
b1z +
b0 !
b0 1
b10 M
b0 C
b10 <
b0 :
b0 8
b10 7
b0 6
b1x J
b0 F
b0 @
b110 ?
b100 >
1$
#420
b10 -
1U
b1 W
1R
b10 5
b1001 #
b1001 &
b1001 I"
0$
#425
1E"
b1 G"
1B"
bz100 '
bz1010 (
bz01000 )
bz000110 *
b10z +
b10 !
b10 1
b10 N
b0 D
b10 =
b0 ;
b10 8
b0 7
b10 6
b100 F
b0 G
b110 @
b100 ?
b10 >
1$
#430
b0 -
0U
b0 W
0R
b0 5
b10 9
b1010 #
b1010 &
b1010 I"
0$
#435
b100 -
1y
b1 {
1w
bz110 '
bz1100 (
bz01010 )
bz001000 *
b11z +
b100 !
b100 1
b10 O
b0 E
b0 <
b10 :
b0 8
b10 7
b0 6
b100 G
b0 H
b100 @
b10 ?
b0 >
1$
#440
b110 -
1U
b1 W
1R
b10 5
b1011 #
b1011 &
b1011 I"
0$
#445
0E"
b0 G"
0B"
bz000 '
bz1110 (
bz01100 )
bz001010 *
b100z +
b110 !
b110 1
b10 P
b0 =
b10 ;
b10 8
b0 7
b10 6
b100 H
b0 I
b10 @
b0 ?
b110 >
1$
#450
b100 -
0U
b110 ,
1-"
b0 W
b1 /"
0R
1*"
b0 5
b0 9
b10 B
b1100 #
b1100 &
b1100 I"
0$
#455
b0 -
0y
0[
b0 {
b0 ]
0w
0Y
bz010 '
bz0000 (
bz01110 )
bz001100 *
b101z +
b1000 !
b1000 1
b10 C
b10 <
b0 :
b0 8
b10 7
b0 6
b100 I
b0x J
b110 F
b0 @
b110 ?
b100 >
1$
#460
b10 -
1U
b1 W
1R
b10 5
b1101 #
b1101 &
b1101 I"
0$
#465
1a
1E"
b1 c
b1 G"
1_
1B"
bz100 '
bz0010 (
bz10000 )
bz001110 *
b110z +
b1010 !
b1010 1
b10 D
b10 =
b0 ;
b10 8
b0 7
b10 6
b10x J
b110 G
b110 @
b100 ?
b10 >
1$
#470
b0 -
0U
b0 W
0R
b0 5
b10 9
b1110 #
b1110 &
b1110 I"
0$
#475
b100 -
1y
b1 {
1w
bz110 '
bz0100 (
bz10010 )
bz010000 *
b111z +
b1100 !
b1100 1
b10 E
b0 <
b10 :
b0 8
b10 7
b0 6
b110 H
b100 @
b10 ?
b0 >
1$
#480
b110 -
1U
b1 W
1R
b10 5
b1111 #
b1111 &
b1111 I"
0$
#485
0E"
b0 G"
0B"
bz000 '
bz0110 (
bz10100 )
bz010010 *
b1000z +
b1110 !
b1110 1
b0 =
b10 ;
b10 8
b0 7
b10 6
b110 I
b10 @
b0 ?
b110 >
1$
#490
b100 -
0U
b100 ,
0-"
b0 W
b0 /"
0R
0*"
b0 5
b0 9
b0 B
b0 L
b0 #
b0 &
b11 "
b11 %
b11 H"
b0 I"
0$
#495
b0 ,
03"
b0 -
0y
1[
b0 5"
b0 {
b1 ]
01"
0w
1Y
bz010 '
bz1000 (
bz10110 )
bz010100 *
b1001z +
b10000 !
b10000 1
b0 M
b0 C
b10 <
b0 :
b0 8
b10 7
b0 6
b11x J
b100 F
b0 @
b110 ?
b100 >
1$
#500
1U
b1 W
b11 -
1R
b11 5
b1 #
b1 &
b1 I"
0$
