fir/mac.v
module mac #(parameter data_width = 8)(
  input clock,
  input reset,
  input [data_width-1:0] rom_out,
  input [data_width-1:0] ram_out,
  input mac_init,
  output reg [data_width*2+2:0] y,
  output reg valid_out
); 

reg [data_width*2+2:0] y_temp;
reg [2:0] counter;

initial begin counter = 0; y_temp = 0; end

assign y = y_temp;
always@(posedge clock) begin
  if(mac_init == 1) y_temp <= {3'b000,rom_out*ram_out};
  else y_temp <= {y_temp + rom_out*ram_out};
end


always@(posedge clock or posedge reset) begin
  if (reset == 1) valid_out <= 0;
  else begin 
    if (mac_init == 1 && counter != 6) begin counter <= 0; valid_out <= 0; end 
    else if (mac_init == 0 && counter == 6) begin counter <= 0; valid_out <= 1; end
    else if (mac_init == 1 && counter == 6) begin counter <= 0; valid_out <= 1; end
    else begin counter <= counter + 1; valid_out <= 0; end 
  end
  
end

endmodule

fir/ram.v
module ram #(parameter data_width =8)(
  input clock,
  input reset,
  input we,
  input en,
  input [2:0] addr,
  input [data_width-1:0] di,
  output reg [data_width-1:0] dio
);

reg [data_width-1:0] ram [0:7];
initial begin 
  ram[0] = 0;
  ram[1] = 0;
  ram[2] = 0;
  ram[3] = 0;
  ram[4] = 0;
  ram[5] = 0;
  ram[6] = 0;
  ram[7] = 0;
end

always @ (posedge clock or posedge reset) begin
  if (reset == 1) 
    for(int i=0;i<data_width;i++) ram[i] = 0;
  else begin 
    if (en == 1) begin 
      if (we == 1) begin
        for(int i=0;i<=data_width-2;i++) ram[i+1] = ram[i];
        ram[0] <= di;
        dio <= di;
      end
      else dio <= ram[addr];
    end 
  end 
end
endmodule

fir/rom.v
module rom #(parameter coeff_width =8)(
  input clock,
  input en,
  input [2:0] addr,
  output reg [coeff_width-1:0] rom_out
);

reg [coeff_width-1:0] rom [0:7] ; 
reg [coeff_width-1:0] rdata;
initial begin
  rom[0] = 8'b00001000; 
  rom[1] = 8'b00000111;
  rom[2] = 8'b00000110; 
  rom[3] = 8'b00000101; 
  rom[4] = 8'b00000100; 
  rom[5] = 8'b00000011; 
  rom[6] = 8'b00000010;
  rom[7] = 8'b00000001;
end
assign rdata = rom[addr];
always@(posedge clock) begin 
  if (en == 1) rom_out <= rdata;
end 
endmodule

fir/control.v
module control_unit(
  input clock,
  input reset,
  input valid_in,
  output reg [2:0] rom_address,
  output reg [2:0] ram_address,
  output reg mac_init,
  output reg we,
  output reg en
);

reg [2:0] counter;
initial counter =0 ; 

always @ (posedge clock or posedge reset) begin
  if (reset == 1) 
    counter <= 0;
  else begin
    if (counter == 0 && valid_in == 1 ) begin
      en = 1;
      we <= 1;
      mac_init <= 1;
      rom_address <= counter;
      ram_address <= counter;
      counter <= counter + 1;
    end
    else if (counter == 0 && valid_in == 0) begin
      we <= 0;
      mac_init <= 1;
      en <= 0;
    end
    else if (counter != 0) begin 
      en <= 1;
      mac_init <= 0;
      we <= 0;
      rom_address <= counter;
      ram_address <= counter;
      counter <= counter + 1;
    end
  end
end
endmodule

fir/fir.v
module fir(
  input clock,
  input reset, 
  input valid_in,
  input [7:0] x,
  output reg [18:0] y,
  output reg valid_out
);

reg [2:0] rom_address_control_unit;
reg [2:0] ram_address_control_unit;
reg mac_init_control_unit;
reg [7:0] ram_out_ram;
reg [7:0] rom_out_rom;
reg en_control_unit;
reg we_control_unit;
reg mac_init_mac;

always@(posedge clock) mac_init_mac <= mac_init_control_unit;

control_unit cudut(.clock(clock),.reset(reset),.valid_in(valid_in),.rom_address(rom_address_control_unit),
                   .ram_address(ram_address_control_unit),.mac_init(mac_init_control_unit),.we(we_control_unit),
                   .en(en_control_unit));
rom romdut(.clock(clock),.en(en_control_unit),.addr(rom_address_control_unit),.rom_out(rom_out_rom));
ram ramdut(.clock(clock),.reset(reset),.we(we_control_unit),.en(en_control_unit),.addr(ram_address_control_unit),.di(x),.dio(ram_out_ram));
mac macdut(.clock(clock),.reset(reset),.rom_out(rom_out_rom),.ram_out(ram_out_ram),.mac_init(mac_init_mac),.y(y),.valid_out(valid_out));
endmodule

fir/fir_tb.sv
module fir_tb;
logic clock;
logic reset;
logic valid_in;
logic [7:0] x;
logic [18:0] y;
logic valid_out;

fir dut(.clock(clock),.reset(reset),.valid_in(valid_in),.x(x),.y(y),.valid_out(valid_out));

always begin #5 clock=0; #5 clock=1; end
initial begin
  $dumpfile("fir.vcd");
  $dumpvars(0, fir_tb);
  reset = 1;
  clock = 1;
  #10 reset =0;

  for(int i=0;i<8;i++) begin
    #10 valid_in = 1;
    x = i; 
  end
  valid_in <=0;
  #100 $finish;
end 
endmodule

fir/fir.vcd
$date
	Fri Aug 18 00:35:50 2023
$end
$version
	Icarus Verilog
$end
$timescale
	1s
$end
$scope module fir_tb $end
$var wire 19 ! y [18:0] $end
$var wire 1 " valid_out $end
$var reg 1 # clock $end
$var reg 1 $ reset $end
$var reg 1 % valid_in $end
$var reg 8 & x [7:0] $end
$scope module dut $end
$var wire 1 # clock $end
$var wire 1 $ reset $end
$var wire 1 % valid_in $end
$var wire 8 ' x [7:0] $end
$var wire 19 ( y [18:0] $end
$var wire 1 ) we_control_unit $end
$var wire 1 " valid_out $end
$var wire 8 * rom_out_rom [7:0] $end
$var wire 3 + rom_address_control_unit [2:0] $end
$var wire 8 , ram_out_ram [7:0] $end
$var wire 3 - ram_address_control_unit [2:0] $end
$var wire 1 . mac_init_control_unit $end
$var wire 1 / en_control_unit $end
$var reg 1 0 mac_init_mac $end
$scope module cudut $end
$var wire 1 # clock $end
$var wire 1 $ reset $end
$var wire 1 % valid_in $end
$var reg 3 1 counter [2:0] $end
$var reg 1 / en $end
$var reg 1 . mac_init $end
$var reg 3 2 ram_address [2:0] $end
$var reg 3 3 rom_address [2:0] $end
$var reg 1 ) we $end
$upscope $end
$scope module macdut $end
$var wire 1 # clock $end
$var wire 1 0 mac_init $end
$var wire 1 $ reset $end
$var wire 19 4 y [18:0] $end
$var wire 8 5 rom_out [7:0] $end
$var wire 8 6 ram_out [7:0] $end
$var parameter 32 7 data_width $end
$var reg 3 8 counter [2:0] $end
$var reg 1 " valid_out $end
$var reg 19 9 y_temp [18:0] $end
$upscope $end
$scope module ramdut $end
$var wire 3 : addr [2:0] $end
$var wire 1 # clock $end
$var wire 8 ; di [7:0] $end
$var wire 1 / en $end
$var wire 1 $ reset $end
$var wire 1 ) we $end
$var parameter 32 < data_width $end
$var reg 8 = dio [7:0] $end
$scope begin $ivl_for_loop1 $end
$var integer 32 > i [31:0] $end
$upscope $end
$scope begin $ivl_for_loop2 $end
$var integer 32 ? i [31:0] $end
$upscope $end
$upscope $end
$scope module romdut $end
$var wire 3 @ addr [2:0] $end
$var wire 1 # clock $end
$var wire 1 / en $end
$var wire 8 A rdata [7:0] $end
$var parameter 32 B coeff_width $end
$var reg 8 C rom_out [7:0] $end
$upscope $end
$upscope $end
$scope begin $ivl_for_loop0 $end
$var integer 32 D i [31:0] $end
$upscope $end
$upscope $end
$enddefinitions $end
$comment Show the parameter values. $end
$dumpall
b1000 B
b1000 <
b1000 7
$end
#0
$dumpvars
b0 D
bx C
bx A
bx @
b0 ?
b1000 >
bx =
bx ;
bx :
bx 9
b0 8
bx 6
bx 5
bx 4
bx 3
bx 2
b0 1
x0
x/
x.
bx -
bx ,
bx +
bx *
x)
bx (
bx '
bx &
x%
1$
1#
0"
bx !
$end
#5
0#
#10
b1 8
1#
0$
#15
0#
#20
b1 1
b0 -
b0 2
b0 :
b1000 A
b0 +
b0 3
b0 @
1.
1)
b10 8
1/
1#
b1 D
b0 &
b0 '
b0 ;
1%
#25
0#
#30
b1 ,
b1 6
b1 =
b11 8
b10 1
b1 -
b1 2
b1 :
b111 A
b1 +
b1 3
b1 @
0)
0.
10
b1000 *
b1000 5
b1000 C
b111 ?
1#
b10 D
b1 &
b1 '
b1 ;
#35
0#
#40
b11 1
b10 -
b10 2
b10 :
b110 A
b10 +
b10 3
b10 @
b0 8
b0 ,
b0 6
b0 =
b111 *
b111 5
b111 C
b1000 !
b1000 (
b1000 4
b1000 9
00
1#
b11 D
b10 &
b10 '
b10 ;
#45
0#
#50
b1 8
b100 1
b11 -
b11 2
b11 :
b101 A
b11 +
b11 3
b11 @
b110 *
b110 5
b110 C
1#
b100 D
b11 &
b11 '
b11 ;
#55
0#
#60
b101 1
b100 -
b100 2
b100 :
b100 A
b100 +
b100 3
b100 @
b10 8
b101 *
b101 5
b101 C
1#
b101 D
b100 &
b100 '
b100 ;
#65
0#
#70
b11 8
b110 1
b101 -
b101 2
b101 :
b11 A
b101 +
b101 3
b101 @
b100 *
b100 5
b100 C
1#
b110 D
b101 &
b101 '
b101 ;
#75
0#
#80
b111 1
b110 -
b110 2
b110 :
b10 A
b110 +
b110 3
b110 @
b100 8
b11 *
b11 5
b11 C
1#
b111 D
b110 &
b110 '
b110 ;
#85
0#
#90
b101 8
b0 1
b111 -
b111 2
b111 :
b1 A
b111 +
b111 3
b111 @
b10 *
b10 5
b10 C
0%
1#
b1000 D
b111 &
b111 '
b111 ;
#95
0#
#100
0/
1.
b110 8
b1 *
b1 5
b1 C
1#
#105
0#
#110
1"
b0 8
10
1#
#115
0#
#120
0"
b0 !
b0 (
b0 4
b0 9
1#
