adder_4bit/test.v
module Adder4Bit (
    input clock,
    input [3:0] A,
    input [3:0] B,
    input cin,
    output reg [3:0] Sum,
    output reg cout
);
    wire [4:0] sum_temp;

    assign sum_temp = A + B + {"000",cin};
    always@(posedge clock) begin
        assign Sum = sum_temp[3:0];
        assign cout = sum_temp[4];
    end 

endmodule

adder_4bit/test_tb.sv
`timescale 1ns/1ns
module tb_Adder4Bit;

  // Declare signals for testbench using logic data type
  logic clock;
  logic [3:0] tb_A;
  logic [3:0] tb_B;
  logic tb_cin;
  logic [3:0] tb_Sum;
  logic tb_cout;

   // Declare file handle for debug logging
   integer debug_file;
  // Instantiate the Adder4Bit module
  Adder4Bit dut (
    .clock(clock),
    .A(tb_A),
    .B(tb_B),
    .cin(tb_cin),
    .Sum(tb_Sum),
    .cout(tb_cout)
  );

  always begin 
    #5 clock = 1;
    $display("Time %5d, clock: %b",$time,clock);
    #5 clock = 0;
    $display("Time %5d, clock: %b",$time,clock);
  end 
  program test;
  // Initialize signals
  initial begin
    debug_file = $fopen("debug_log.txt", "w");
    $dumpfile("test.vcd");
    $dumpvars(0, tb_Adder4Bit);
    tb_A = 4'b0000;
    tb_B = 4'b0011;
    tb_cin = 1'b1;
    clock = 1'b0;
    // Display header
    $display("Time | A | B | Cin | Sum | Cout");
    $fdisplay(debug_file,"Time | A | B | Cin | Sum | Cout");

    // Display results and add assertions for each simulation cycle
    for (int i = 0; i < 8; i = i + 1) begin
      #10;
      $display("%4t | %d | %d | %d | %d | %d ", $time, tb_A, tb_B, tb_cin, tb_Sum, tb_cout);
      $fdisplay(debug_file,"%4t | %d | %d | %d | %d | %d", $time, tb_A, tb_B, tb_cin, tb_Sum, tb_cout);

      // Update inputs for the next cycle
      tb_A = tb_A + 1;
      tb_B = tb_B + 1;
      tb_cin = ~tb_cin; // Alternate carry-in value
    end


    // End simulation
    $finish;
    $fclose(debug_file);

  end
  endprogram

endmodule

adder_4bit/test.vcd
$date
	Tue Aug 15 23:06:22 2023
$end
$version
	Icarus Verilog
$end
$timescale
	1ns
$end
$scope module tb_Adder4Bit $end
$var wire 1 ! tb_cout $end
$var wire 4 " tb_Sum [3:0] $end
$var reg 1 # clock $end
$var reg 4 $ tb_A [3:0] $end
$var reg 4 % tb_B [3:0] $end
$var reg 1 & tb_cin $end
$var integer 32 ' debug_file [31:0] $end
$scope module dut $end
$var wire 4 ( A [3:0] $end
$var wire 4 ) B [3:0] $end
$var wire 1 & cin $end
$var wire 1 # clock $end
$var wire 5 * sum_temp [4:0] $end
$var reg 4 + Sum [3:0] $end
$var reg 1 ! cout $end
$upscope $end
$scope module test $end
$scope begin $ivl_for_loop0 $end
$var integer 32 , i [31:0] $end
$upscope $end
$upscope $end
$upscope $end
$enddefinitions $end
$comment Show the parameter values. $end
$dumpall
$end
#0
$dumpvars
b0 ,
bx +
b100 *
b11 )
b0 (
b10000000000000000000000000000011 '
1&
b11 %
b0 $
0#
bx "
x!
$end
#5
0!
b100 "
b100 +
1#
#10
b101 *
0#
b1 ,
0&
b100 %
b100 )
b1 $
b1 (
#15
b101 "
b101 +
1#
#20
b1000 *
0#
b10 ,
1&
b101 %
b101 )
b10 $
b10 (
#25
b1000 "
b1000 +
1#
#30
b1001 *
0#
b11 ,
0&
b110 %
b110 )
b11 $
b11 (
#35
b1001 "
b1001 +
1#
#40
b1100 *
0#
b100 ,
1&
b111 %
b111 )
b100 $
b100 (
#45
b1100 "
b1100 +
1#
#50
b1101 *
0#
b101 ,
0&
b1000 %
b1000 )
b101 $
b101 (
#55
b1101 "
b1101 +
1#
#60
b10000 *
0#
b110 ,
1&
b1001 %
b1001 )
b110 $
b110 (
#65
1!
b0 "
b0 +
1#
#70
b10001 *
0#
b111 ,
0&
b1010 %
b1010 )
b111 $
b111 (
#75
b1 "
b1 +
1#
#80
b10100 *
0#
b1000 ,
1&
b1011 %
b1011 )
b1000 $
b1000 (
